edrift/__init__.py
edrift-0.0.0.dist-info/METADATA
edrift-0.0.0.dist-info/WHEEL
edrift-0.0.0.dist-info/top_level.txt
edrift-0.0.0.dist-info/RECORD
