Metadata-Version: 2.1
Name: edrift
Version: 0.0.0
Summary: edrift watershed modeling
Home-page: https://github.com/aerispaha/edrift
Author: 
Author-email: 
License: MIT License
Platform: OS Independent
Classifier: Development Status :: 3 - Alpha
Classifier: License :: OSI Approved :: MIT License
Classifier: Operating System :: OS Independent
Classifier: Programming Language :: Python :: 3.6
Classifier: Programming Language :: Python :: 3.7
